openai_api_utils/__init__.py
openai_api_utils/api/__init__.py
openai_api_utils/api/_tools.py
openai_api_utils/api/util.py
openai_api_utils/function_call/__init__.py
openai_api_utils/function_call/acts.py
openai_api_utils/function_call/functions.py
openai_api_utils/function_call/resources.py
openai_api_utils-0.0.2.dist-info/LICENSE
openai_api_utils-0.0.2.dist-info/METADATA
openai_api_utils-0.0.2.dist-info/WHEEL
openai_api_utils-0.0.2.dist-info/top_level.txt
openai_api_utils-0.0.2.dist-info/RECORD
